Workbook

Sheet Dashboard
D2: PULAU PANGKOR TRIP
A3: PANGKOR TRIP
D4: 29 - 31 August 2026 | 3 Days 2 Nights
A6: DASHBOARD | D6: TRIP DATES | F6: NUMBER OF PAX | H6: COST / PERSON (RM) | J6: STATUS
D8: 29-31 Aug | F8: =IFERROR(Financial!C7,"-") -> 6 | H8: =IFERROR(Financial!C8,"-") -> 187 | J8: Planning
A9: TENTATIVE
D11: FINANCIAL SUMMARY
A12: LOGISTIC | D12: Total Collected (RM) | F12: Total Expenses (RM) | H12: Balance (RM) | J12: Need to Collected
D13: =Financial!C9 -> 962 | F13: =Financial!C24 -> 1130.04 | H13: =Financial!C10 -> 211.97 | J13: =Financial!C11 -> -160
A15: FINANCIAL
D16: EXPENSE BREAKDOWN
D17: Item | G17: Amount (RM)
D18: Hotel | G18: =IFERROR(Financial!C16,0) -> 415.02
D19: Oil and Toll | G19: =IFERROR(Financial!C17,0) -> 180
D20: Rent a Motor | G20: =IFERROR(Financial!C18,0) -> 400.02
D21: Ticket Ferry | G21: =IFERROR(Financial!C19,0) -> 135
D22: Total | G22: =IFERROR(Financial!C24,0) -> 1130.04
A29: Pulau Pangkor Aug 2026

Sheet Tentative
A1: ← Dashboard
A3: TENTATIVE ITINERARY
A4: Pulau Pangkor Trip | 29 - 31 August 2026
A6: DAY 1 - SATURDAY, 29 AUGUST 2026
A7: Time | B7: Activity | C7: Location | D7: Notes / PIC
A15: DAY 2 - SUNDAY, 30 AUGUST 2026
A16: Time | B16: Activity | C16: Location | D16: Notes / PIC
A24: DAY 3 - MONDAY, 31 AUGUST 2026
A25: Time | B25: Activity | C25: Location | D25: Notes / PIC

Sheet Logistic
A1: ← Dashboard
A3: LOGISTIC
A4: Transport, accommodation & packing checklist
A6: TRANSPORTATION
A7: Item | B7: Details | C7: PIC | D7: Status | E7: Notes
A14: ACCOMMODATION
A15: Hotel Name
A16: Address
A17: Check-in
A18: Check-out
A19: Contact No.
A21: PACKING / EQUIPMENT CHECKLIST
A22: Item | B22: Qty | C22: Assigned To | D22: Status | E22: Notes
A30: EMERGENCY CONTACTS
A31: Name | B31: Role | C31: Phone

Sheet Financial
A1: ← Dashboard
A3: FINANCIAL
A4: Pulau Pangkor Trip | 29 - 31 August 2026
A6: CONTRIBUTION
A7: Number of Pax | C7: 6
A8: Cost per Person (RM) | C8: 187
A9: Total Actual Collected | C9: =C33 -> 962
A10: Balance After Paid | C10: {=$C$9-SUMIF(D16:D23,"PAID",C16:C23)-SUMPRODUCT((D16:D23="HALF")*C16:C23/2)} -> 211.97
A11: Balance Need to Collected | C11: =C9-C12 -> -160
A12: Total Collected (RM) | C12: =IFERROR(C7*C8,0) -> 1122
A14: EXPENSES
A15: Item | C15: Amount (RM) | D15: Notes
A16: Hotel | C16: =69.17*6 -> 415.02 | D16: PAID
A17: Oil and Toll | C17: =30*6 -> 180
A18: Rent a Motor | C18: =66.67*6 -> 400.02 | D18: HALF
A19: Ticket Ferry | C19: =22.5*6 -> 135 | D19: PAID
A24: TOTAL EXPENSES | C24: =SUM(C16:C23) -> 1130.04
A26: EACH PERSON PAID
A27: IRFAN | C27: 109
A28: HARITH | C28: 149
A29: SHAD | C29: 149
A30: POJI | C30: 187
A31: AGA | C31: 181
A32: BHRAMA | C32: 187
A33: Total Collected | C33: =SUM(C27:C32) -> 962
A35: BALANCE EACH PERSON NEED TO PAY
A36: IRFAN | C36: =C27-$C$8 -> -78
A37: HARITH | C37: =C28-$C$8 -> -38
A38: SHAD | C38: =C29-$C$8 -> -38
A39: POJI | C39: =C30-$C$8 -> 0
A40: AGA | C40: =C31-$C$8 -> -6
A41: BHRAMA | C41: =C32-$C$8 -> 0
A42: Total Collected | C42: =SUM(C36:C41) -> -160
